README.txt
setup.py
silly_content_generator.py
silly_content_generator.egg-info/PKG-INFO
silly_content_generator.egg-info/SOURCES.txt
silly_content_generator.egg-info/dependency_links.txt
silly_content_generator.egg-info/entry_points.txt
silly_content_generator.egg-info/requires.txt
silly_content_generator.egg-info/top_level.txt