Metadata-Version: 1.0
Name: silly-content-generator
Version: 1.0
Summary: A tool to generate sample website content
Home-page: https://github.com/aclark4life/silly_content_generator
Author: Alex Clark
Author-email: aclark@aclark.net
License: UNKNOWN
Platform: UNKNOWN
